localsend/__init__.py
localsend/__main__.py
localsend/app.py
localsend/callbacks.py
localsend/config.py
localsend/info.py
localsend/py.typed
localsend/upload.py
localsend/lib/datadir.py
localsend/lib/dto.py
localsend/lib/resources.py
localsend/lib/http_protocol/endpoints.py
localsend/lib/proto/endpoints.py
localsend/lib/protocol/__init__.py
localsend/lib/protocol/client.py
localsend/lib/protocol/device.py
localsend/lib/protocol/endpoints.py
localsend/lib/protocol/server.py
localsend/lib/ssl/__init__.py
localsend/lib/ssl/context.py
localsend/lib/ssl/rsa.py
localsend/lib/ssl/x509.py
localsend/lib/util/__init__.py
localsend/lib/util/a_sync.py
localsend/lib/util/context.py
localsend/lib/util/error.py
localsend/lib/util/file.py
localsend/lib/util/log.py
localsend/lib/util/seralization.py
localsend/lib/util/time.py
localsend/resources/adjectives.txt
localsend/resources/object_names.txt
localsend/tasks/__init__.py
localsend/tasks/http_server.py
localsend/tasks/multicast.py
localsend-0.1.2.dist-info/METADATA
localsend-0.1.2.dist-info/WHEEL
localsend-0.1.2.dist-info/entry_points.txt
localsend-0.1.2.dist-info/RECORD
