Metadata-Version: 2.4
Name: localsend
Version: 0.1.2
Summary: Implementation of the localsend protocol
Author-email: Florian Daude <floriandaude@hotmail.fr>
License-Expression: MIT
Requires-Python: >=3.12
Requires-Dist: aiofiles>=24.1.0
Requires-Dist: cryptography>=44.0.3
Requires-Dist: httpx>=0.28.1
Requires-Dist: multicast-expert>=1.6.0
Requires-Dist: platformdirs>=4.3.7
Requires-Dist: pydantic>=2.11.4
Requires-Dist: starlette>=0.46.2
Requires-Dist: uvicorn>=0.34.2
Provides-Extra: cli
Requires-Dist: cyclopts>=3.16.0; extra == 'cli'
Requires-Dist: slcfg>=0.3.4; extra == 'cli'
